mediagrains/__init__.py
mediagrains/_version.py
mediagrains/cogenums.py
mediagrains/gsf.py
mediagrains/py.typed
mediagrains/typing.py
mediagrains/comparison/__init__.py
mediagrains/comparison/__main__.py
mediagrains/comparison/_internal.py
mediagrains/comparison/options.py
mediagrains/comparison/psnr.py
mediagrains/comparison/py.typed
mediagrains/grains/AudioGrain.py
mediagrains/grains/CodedAudioGrain.py
mediagrains/grains/CodedVideoGrain.py
mediagrains/grains/EventGrain.py
mediagrains/grains/Grain.py
mediagrains/grains/VideoGrain.py
mediagrains/grains/__init__.py
mediagrains/hypothesis/__init__.py
mediagrains/hypothesis/py.typed
mediagrains/hypothesis/strategies.py
mediagrains/numpy/__init__.py
mediagrains/numpy/convert.py
mediagrains/numpy/py.typed
mediagrains/numpy/numpy_grains/AudioGrain.py
mediagrains/numpy/numpy_grains/VideoGrain.py
mediagrains/numpy/numpy_grains/__init__.py
mediagrains/patterngenerators/__init__.py
mediagrains/patterngenerators/abc.py
mediagrains/patterngenerators/py.typed
mediagrains/patterngenerators/audio/__init__.py
mediagrains/patterngenerators/audio/abc.py
mediagrains/patterngenerators/audio/py.typed
mediagrains/patterngenerators/audio/tone.py
mediagrains/patterngenerators/video/__init__.py
mediagrains/patterngenerators/video/abc.py
mediagrains/patterngenerators/video/colourbars.py
mediagrains/patterngenerators/video/constants.py
mediagrains/patterngenerators/video/lumasteps.py
mediagrains/patterngenerators/video/movingbaroverlay.py
mediagrains/patterngenerators/video/py.typed
mediagrains/patterngenerators/video/still.py
mediagrains/tools/__init__.py
mediagrains/tools/_file_or_pipe.py
mediagrains/tools/extract_from_gsf.py
mediagrains/tools/py.typed
mediagrains/tools/wrap_in_gsf.py
mediagrains/utils/__init__.py
mediagrains/utils/adts_aac_grain_wrapper.py
mediagrains/utils/adts_aac_parser.py
mediagrains/utils/asyncbinaryio.py
mediagrains/utils/grain_wrapper.py
mediagrains/utils/h264_grain_wrapper.py
mediagrains/utils/h264_parser.py
mediagrains-5.1.0.dist-info/COPYING
mediagrains-5.1.0.dist-info/LICENSE.md
mediagrains-5.1.0.dist-info/METADATA
mediagrains-5.1.0.dist-info/WHEEL
mediagrains-5.1.0.dist-info/entry_points.txt
mediagrains-5.1.0.dist-info/top_level.txt
mediagrains-5.1.0.dist-info/RECORD
