Metadata-Version: 2.1
Name: mediagrains
Version: 5.1.0
Summary: Simple utility for grain-based media
Home-page: https://github.com/bbc/rd-apmm-python-lib-mediagrains
Author: BBC R&D
Author-email: cloudfit-opensource@rd.bbc.co.uk
License: Apache 2
Requires-Python: >=3.10.0
License-File: LICENSE.md
License-File: COPYING
Requires-Dist: mediajson >=2.0.0
Requires-Dist: mediatimestamp >=2.1.0
Requires-Dist: frozendict >=1.2
Requires-Dist: numpy >=1.23.0
Requires-Dist: deprecated >=1.2.6
Requires-Dist: bitstring >=4.1.0
